bmb_cron_private_keys/__init__.py
bmb_cron_private_keys/version.py
bmb_cron_private_keys-0.0.2.dist-info/METADATA
bmb_cron_private_keys-0.0.2.dist-info/WHEEL
bmb_cron_private_keys-0.0.2.dist-info/top_level.txt
bmb_cron_private_keys-0.0.2.dist-info/RECORD
